proc/__init__.py
proc/apache.py
proc/core.py
proc/cron.py
proc/gpg.py
proc/notify.py
proc/tests.py
proc/tree.py
proc/unix.py
proc-1.0.dist-info/LICENSE.txt
proc-1.0.dist-info/METADATA
proc-1.0.dist-info/WHEEL
proc-1.0.dist-info/entry_points.txt
proc-1.0.dist-info/top_level.txt
proc-1.0.dist-info/RECORD
